adafruit_debouncer.py
adafruit_circuitpython_debouncer-2.0.13.dist-info/licenses/LICENSE
adafruit_circuitpython_debouncer-2.0.13.dist-info/METADATA
adafruit_circuitpython_debouncer-2.0.13.dist-info/WHEEL
adafruit_circuitpython_debouncer-2.0.13.dist-info/top_level.txt
adafruit_circuitpython_debouncer-2.0.13.dist-info/RECORD
